ezpip/__init__.py
ezpip/test.py
ezpip/_develop_dummy_module/dummy.py
ezpip/parts/config.py
ezpip/parts/dummy_python_file.py
ezpip/parts/load_develop.py
ezpip/parts/import_test_field/test.py
ezpip/parts/import_test_field/hoge_module/__init__.py
ezpip-0.2.3.dist-info/METADATA
ezpip-0.2.3.dist-info/WHEEL
ezpip-0.2.3.dist-info/top_level.txt
ezpip-0.2.3.dist-info/RECORD
