Metadata-Version: 2.1
Name: ezpip
Version: 0.2.3
Summary: This is a tool for easy pip publishing. (Makes it easy to list `packages`.)
Home-page: https://github.co.jp/
Author: le_lattelle
Author-email: g.tiger.ml@gmail.com
License: CC0 v1.0
Platform: UNKNOWN
Classifier: Programming Language :: Python :: 3
Classifier: Topic :: Software Development :: Libraries
Classifier: License :: CC0 1.0 Universal (CC0 1.0) Public Domain Dedication
Requires-Dist: relpath
Requires-Dist: sout
Requires-Dist: fies
